{
  "sourceId": "confuciusAnalects",
  "displayName": "Analects of Confucius",
  "version": "1.0",
  "languageCode": "en",
  "displayNameEnglish": null,
  "script": null,
  "isRTL": false,
  "transliterationAvailable": false,
  "contentRating": null,
  "language": "English",
  "edition": "James Legge Translation, 1861",
  "primaryCategory": "Philosophy & Thought",
  "subcategory": "Confucian",
  "audienceTags": [
    "philosophy",
    "ethics"
  ],
  "itemCount": 370,
  "supportsRandom": true,
  "supportsBrowse": true,
  "browseOrder": "sequence",
  "packageUrl": "https://raw.githubusercontent.com/kiritv/QuoteIt/main/Datasets/packages/en/confuciusAnalects.quoteit",
  "isFeatured": false,
  "priority": 9999,
  "generatedAt": "2026-03-08T18:37:53Z"
}
