{
  "kind": "datasets",
  "language": "ja",
  "count": 4,
  "generatedAt": "2026-03-11T17:40:19Z",
  "items": [
    {
      "sourceId": "bashoHaiku",
      "displayName": "松尾芭蕉 俳句",
      "version": "1.0",
      "languageCode": "ja",
      "displayNameEnglish": "Haiku Masters — Japanese",
      "script": "CJK",
      "isRTL": false,
      "transliterationAvailable": false,
      "contentRating": "general",
      "language": "Japanese",
      "edition": "Basho, Buson, Issa & Shiki",
      "primaryCategory": null,
      "subcategory": "Haiku",
      "audienceTags": [
        "tradition:japanese",
        "genre:haiku",
        "theme:nature"
      ],
      "itemCount": 300,
      "supportsRandom": true,
      "supportsBrowse": true,
      "browseOrder": "author",
      "packageUrl": "https://raw.githubusercontent.com/kiritv/QuoteIt/main/Datasets/packages/ja/bashoHaiku.quoteit",
      "isFeatured": false,
      "priority": 9999,
      "generatedAt": "2026-03-11T17:40:19Z",
      "packageHash": "d6e189dba6b574b4108700ab5b759668622e295689f94eca723d814d3015fae3"
    },
    {
      "sourceId": "bushidoWisdom",
      "displayName": "武士道の知恵",
      "version": "1.0",
      "languageCode": "ja",
      "displayNameEnglish": "Bushido — The Way of the Warrior",
      "script": "CJK",
      "isRTL": false,
      "transliterationAvailable": false,
      "contentRating": "general",
      "language": "Japanese",
      "edition": "Hagakure, Musashi & Nitobe",
      "primaryCategory": null,
      "subcategory": "Bushido",
      "audienceTags": [
        "tradition:samurai",
        "tradition:bushido",
        "theme:honor",
        "theme:discipline"
      ],
      "itemCount": 300,
      "supportsRandom": true,
      "supportsBrowse": true,
      "browseOrder": "author",
      "packageUrl": "https://raw.githubusercontent.com/kiritv/QuoteIt/main/Datasets/packages/ja/bushidoWisdom.quoteit",
      "isFeatured": false,
      "priority": 9999,
      "generatedAt": "2026-03-11T17:40:19Z",
      "packageHash": "c1fe355afd353ca543650a6d5838c8ab70e8bb819c12d4b2e2741a83476fd780"
    },
    {
      "sourceId": "modernJapanese",
      "displayName": "現代日本語の名言",
      "version": "1.0",
      "languageCode": "ja",
      "displayNameEnglish": "Modern Japanese Voices",
      "script": "CJK",
      "isRTL": false,
      "transliterationAvailable": false,
      "contentRating": "general",
      "language": "Japanese",
      "edition": "Murakami, Miyazaki, Honda & More",
      "primaryCategory": null,
      "subcategory": "Japanese",
      "audienceTags": [
        "era:modern",
        "tradition:japanese",
        "theme:innovation",
        "theme:creativity"
      ],
      "itemCount": 601,
      "supportsRandom": true,
      "supportsBrowse": true,
      "browseOrder": "author",
      "packageUrl": "https://raw.githubusercontent.com/kiritv/QuoteIt/main/Datasets/packages/ja/modernJapanese.quoteit",
      "isFeatured": false,
      "priority": 9999,
      "generatedAt": "2026-03-11T17:40:19Z",
      "packageHash": "e06e3f488b31dd68ce83d8bfdc9611c91e1ecc0713b1206a81a44c21b0d46d95"
    },
    {
      "sourceId": "zenJapanese",
      "displayName": "禅の言葉",
      "version": "1.0",
      "languageCode": "ja",
      "displayNameEnglish": "Zen Masters — Japanese",
      "script": "CJK",
      "isRTL": false,
      "transliterationAvailable": false,
      "contentRating": "devotional",
      "language": "Japanese",
      "edition": "Dogen, Hakuin, Bankei & Classical Masters",
      "primaryCategory": null,
      "subcategory": "Zen",
      "audienceTags": [
        "tradition:zen",
        "tradition:buddhist",
        "theme:mindfulness",
        "theme:awakening"
      ],
      "itemCount": 500,
      "supportsRandom": true,
      "supportsBrowse": true,
      "browseOrder": "author",
      "packageUrl": "https://raw.githubusercontent.com/kiritv/QuoteIt/main/Datasets/packages/ja/zenJapanese.quoteit",
      "isFeatured": false,
      "priority": 9999,
      "generatedAt": "2026-03-11T17:40:19Z",
      "packageHash": "ee34e3feeb1cecbef38803f8215bac5596dec25d221ac75a865986090474f7c6"
    }
  ]
}
